README.rst
setup.py
canary/__init__.py
canary/format.py
canary/handler.py
canary/middleware.py
canary/util.py
canary.egg-info/PKG-INFO
canary.egg-info/SOURCES.txt
canary.egg-info/dependency_links.txt
canary.egg-info/not-zip-safe
canary.egg-info/requires.txt
canary.egg-info/top_level.txt
canary/tests/__init__.py
canary/tests/test_logging.py
canary/tests/test_middleware.py
canary/tests/test_util.py