Metadata-Version: 1.0
Name: canary
Version: 0.1.3
Summary: canary is a small library for recording and shipping exceptions from Python to logstash via ZeroMQ.
Home-page: http://github.com/ryanpetrello/canary
Author: Ryan Petrello
Author-email: ryan@ryanpetrello.com
License: MIT
Keywords: web framework wsgi logstash logging zeromq
Platform: UNKNOWN
Classifier: Development Status :: 5 - Production/Stable
Classifier: Environment :: Console
Classifier: Environment :: Web Environment
Classifier: Intended Audience :: Developers
Classifier: Intended Audience :: System Administrators
Classifier: License :: OSI Approved :: MIT License
Classifier: Operating System :: MacOS :: MacOS X
Classifier: Operating System :: Microsoft :: Windows
Classifier: Operating System :: POSIX
Classifier: Programming Language :: Python
Classifier: Programming Language :: Python :: 2.6
Classifier: Programming Language :: Python :: 2.7
Classifier: Topic :: Internet :: WWW/HTTP :: WSGI
Classifier: Topic :: Software Development :: Libraries :: Application Frameworks
